CLI_passthrough-0.1.2.dist-info/METADATA
CLI_passthrough-0.1.2.dist-info/RECORD
CLI_passthrough-0.1.2.dist-info/WHEEL
CLI_passthrough-0.1.2.dist-info/entry_points.txt
CLI_passthrough-0.1.2.dist-info/top_level.txt
cli_passthrough/__init__.py
cli_passthrough/cli.py
cli_passthrough/passthrough.py
cli_passthrough/utils.py
