Metadata-Version: 2.1
Name: CLI-passthrough
Version: 0.1.2
Summary: Importable CLI-passthrough with bells and whistles.
Home-page: https://github.com/terminal-labs/cli-passthrough
Author: Terminal Labs
Author-email: solutions@terminallabs.com
License: BSD-3-Clause
Keywords: cli utilities logging pty subprocess terminal
Platform: UNKNOWN
Classifier: Environment :: Console
Classifier: Intended Audience :: Developers
Classifier: License :: OSI Approved :: BSD License
Classifier: Topic :: Utilities
Requires-Dist: click
